sketch_converter/__init__.py
sketch_converter/cli.py
sketch_converter/sketch.py
sketch_converter-0.1.1.dist-info/WHEEL
sketch_converter-0.1.1.dist-info/LICENSE
sketch_converter-0.1.1.dist-info/METADATA
sketch_converter-0.1.1.dist-info/entry_points.txt
sketch_converter-0.1.1.dist-info/RECORD
