Metadata-Version: 2.1
Name: sketch-converter
Version: 0.1.1
Summary: Converter your picture into sketch with just one line of command
Home-page: https://github.com/samyak-jn/sketch-converter
License: MIT
Keywords: opencv,sketch-converter,sketch,camera,image
Author: Onuralp SEZER
Author-email: thunderbirdtr@fedoraproject.org
Maintainer: Samyak Jain
Maintainer-email: samyak.jn11@gmail.com
Requires-Python: >=3.8,<4.0
Classifier: Development Status :: 4 - Beta
Classifier: Environment :: X11 Applications
Classifier: License :: OSI Approved :: MIT License
Classifier: Natural Language :: English
Classifier: Operating System :: OS Independent
Classifier: Programming Language :: Python :: 3
Classifier: Programming Language :: Python :: 3.8
Classifier: Programming Language :: Python :: 3.9
Classifier: Programming Language :: Python :: 3.10
Classifier: Programming Language :: Python :: 3.11
Classifier: Programming Language :: Python :: 3.10
Classifier: Programming Language :: Python :: 3.8
Classifier: Programming Language :: Python :: 3.9
Requires-Dist: colorama (>=0.4.6,<0.5.0)
Requires-Dist: commonmark (>=0.9.1,<0.10.0)
Requires-Dist: numpy (>=1.24.1,<2.0.0)
Requires-Dist: opencv-python (>=4.7.0.68,<5.0.0.0)
Requires-Dist: pygments (>=2.14.0,<3.0.0)
Requires-Dist: rich (>=13.0.0,<14.0.0)
Requires-Dist: shellingham (>=1.5.0.post1,<2.0.0)
Requires-Dist: typer (>=0.7.0,<0.8.0)
Project-URL: Documentation, https://github.com/samyak-jn/sketch-converter/blob/main/README.md
Project-URL: Repository, https://github.com/samyak-jn/sketch-converter
